keg_mail/__init__.py
keg_mail/cli.py
keg_mail/content.py
keg_mail/mailgun.py
keg_mail/model.py
keg_mail/plugin.py
keg_mail/utils.py
keg_mail/version.py
keg_mail/views.py
keg_mail/tests/__init__.py
keg_mail/tests/conftest.py
keg_mail/tests/test_content.py
keg_mail/tests/test_mailgun.py
keg_mail/tests/test_plugin.py
keg_mail/tests/test_views.py
keg_mail_ta/__init__.py
keg_mail_ta/app.py
keg_mail_ta/config.py
keg_mail_ta/views.py
keg_mail_ta/model/__init__.py
keg_mail_ta/model/entities.py
Keg_Mail-0.3.1.dist-info/LICENSE
Keg_Mail-0.3.1.dist-info/METADATA
Keg_Mail-0.3.1.dist-info/WHEEL
Keg_Mail-0.3.1.dist-info/top_level.txt
Keg_Mail-0.3.1.dist-info/zip-safe
Keg_Mail-0.3.1.dist-info/RECORD
