Metadata-Version: 2.1
Name: Keg-Mail
Version: 0.3.1
Summary: A mail sending library for keg applications
Home-page: https://github.com/level12/keg-mail
Author: Level 12 Developers
Author-email: devteam@level12.io
License: BSD
Platform: UNKNOWN
Classifier: Intended Audience :: Developers
Classifier: License :: OSI Approved :: BSD License
Classifier: Operating System :: OS Independent
Classifier: Programming Language :: Python :: 3.7
Classifier: Programming Language :: Python :: 3.8
Classifier: Programming Language :: Python :: 3.9
Classifier: Programming Language :: Python :: 3.10
License-File: LICENSE
Requires-Dist: flask-mail (>=0.10.0)
Requires-Dist: Keg
Requires-Dist: SQLAlchemy-Utils
Requires-Dist: arrow
Provides-Extra: mailgun
Requires-Dist: requests ; extra == 'mailgun'
Requires-Dist: ordered-set ; extra == 'mailgun'
Provides-Extra: test
Requires-Dist: tox ; extra == 'test'
Requires-Dist: pytest ; extra == 'test'
Requires-Dist: pytest-coverage ; extra == 'test'
Requires-Dist: requests-mock ; extra == 'test'
Requires-Dist: flask-webtest ; extra == 'test'
Requires-Dist: KegElements ; extra == 'test'
